<annotation><folder>/mnt/hd1/jjmuliana/datasets/ds_31mar2020/images</folder><filename>image_27234.jpg</filename><source><database>MS COCO 2014</database><annotation>MS COCO 2014</annotation><image>Flickr</image></source><size><width>960</width><height>1280</height><depth>3</depth></size><segmented>0</segmented><object><name>FRENTEESQUERDA</name><bndbox><xmin>962</xmin><ymin>585</ymin><xmax>1139</xmax><ymax>711</ymax></bndbox></object><object><name>FRENTEDIREITA</name><bndbox><xmin>35</xmin><ymin>572</ymin><xmax>257</xmax><ymax>728</ymax></bndbox></object></annotation>